{
    "$schema": "https://json.schemastore.org/block.json",
    "apiVersion": 2,
    "name": "wavy/wavy-divider",
    "version": "0.1.0",
    "title": "Wavy Divider",
    "category": "design",
    "description": "A colorful, fun, lightweight divider block to energize your website with character and pizazz",
    "supports": {
        "html": false,
        "align": ["full", "wide"],
        "color": {
            "background": true,
            "gradients": false,
            "text": false
        }
    },
    "textdomain": "ebb-separators",
    "editorScript": "file:./build/index.js",
    "editorStyle": "file:./build/index.css",
    "style": "file:./build/style-index.css"
}
